longevity_factors_by_country/.ipynb_checkpoints/DB Connect and File Upload -checkpoint.ipynb
longevity_factors_by_country/2011 Longevity Data
longevity_factors_by_country/2019 Longevity Data
longevity_factors_by_country/__init__.py
longevity_factors_by_country/clean_data.py
longevity_factors_by_country/database/config.py
longevity_factors_by_country/database/create_tables.py
longevity_factors_by_country/database/pg_connect.py
longevity_factors_by_country/longevity_factors_by_country.py
longevity_factors_by_country-0.1.6.dist-info/LICENSE
longevity_factors_by_country-0.1.6.dist-info/METADATA
longevity_factors_by_country-0.1.6.dist-info/WHEEL
longevity_factors_by_country-0.1.6.dist-info/RECORD
